repo_tmp_aitor/__init__.py
repo_tmp_aitor/sum.py
repo_tmp_aitor-0.0.2.dist-info/METADATA
repo_tmp_aitor-0.0.2.dist-info/WHEEL
repo_tmp_aitor-0.0.2.dist-info/top_level.txt
repo_tmp_aitor-0.0.2.dist-info/RECORD
