Metadata-Version: 2.4
Name: repo-tmp-aitor
Version: 0.0.2
Summary: Proyecto de Gitlab
Author-email: Aitor <author@example.com>
License-Expression: MIT
Project-URL: Homepage, https://gitlab.com/aurrutiadelu/aitor_tmp
Project-URL: Issues, https://gitlab.com/aurrutiadelu/aitor_tmp/-/issues
Classifier: Programming Language :: Python :: 3
Classifier: Operating System :: OS Independent
Requires-Python: >=3.9
